dictum/__init__.py
dictum-0.1.7.dist-info/WHEEL
dictum-0.1.7.dist-info/METADATA
dictum-0.1.7.dist-info/RECORD
