Metadata-Version: 2.1
Name: dictum
Version: 0.1.7
Summary: Describe business metrics with YAML, query and visualize in Jupyter with zero SQL
Author: Mikhail Akimov
Author-email: rovinj.akimov@gmail.com
Requires-Python: >=3.8,<4
Classifier: Programming Language :: Python :: 3
Classifier: Programming Language :: Python :: 3.8
Classifier: Programming Language :: Python :: 3.9
Classifier: Programming Language :: Python :: 3.10
Provides-Extra: postgres
Provides-Extra: vertica
Requires-Dist: dictum-backend-postgres (==0.1.4); extra == "postgres"
Requires-Dist: dictum-backend-vertica (==0.1.3); extra == "vertica"
Requires-Dist: dictum-core (==0.1.8)
